{
	"amounts": {
		"maxDaysAgo": 0
	},
	"choices": {
		"lastMessageDateLang": "en-GB"
	},
	"dates": {
		"lastMessageDate": {}
	},
	"formats": {
		"ownFormat": "$hour: $minute: $second, $day.$month.$year"
	},
	"general": {
		"displayText": true
	},
	"places": {
		"userPopout": true,
		"userProfile": true
	},
	"settings": {
		"addInUserPopout": true,
		"addInUserProfil": false,
		"cutSeconds": false,
		"displayDate": true,
		"displayText": true,
		"displayTime": false,
		"forceZeros": false,
		"otherOrder": false
	}
}